cosmograph/__about__.py
cosmograph/__init__.py
cosmograph/base.py
cosmograph/config.py
cosmograph/util.py
cosmograph/validation.py
cosmograph/data/color_names.json
cosmograph/data/params_ssot.json
cosmograph/widget/__init__.py
cosmograph/widget/utils.py
cosmograph/widget/export_project/__init__.py
cosmograph/widget/export_project/config.py
cosmograph/widget/export_project/create_project.py
cosmograph/widget/export_project/prepare_parquet.py
cosmograph/widget/export_project/upload_file.py
cosmograph/widget/static/meta.json
cosmograph/widget/static/widget-H7JP6AYK.js
cosmograph/widget/static/widget-XOCNYNEO.css
cosmograph-0.5.3.dist-info/METADATA
cosmograph-0.5.3.dist-info/WHEEL
cosmograph-0.5.3.dist-info/licenses/LICENSE
cosmograph-0.5.3.dist-info/RECORD
