Metadata-Version: 2.4
Name: cosmograph
Version: 0.5.3
Summary: Visualize large-scale network graphs and machine learning embeddings
License-Expression: GPL-3.0-or-later
License-File: LICENSE
Keywords: Embedding,Graph,Machine Learning,Network,Visualization
Requires-Dist: anywidget
Requires-Dist: dol>=0.3.30
Requires-Dist: i2>=0.1.58
Requires-Dist: joblib
Requires-Dist: ju>=0.1.31
Requires-Dist: numpy
Requires-Dist: pandas
Requires-Dist: pyarrow
Requires-Dist: tabled>=0.1.26
Requires-Dist: traitlets
Provides-Extra: dev
Requires-Dist: jupyterlab; extra == 'dev'
Requires-Dist: watchfiles; extra == 'dev'
Provides-Extra: dev-utils
Requires-Dist: hubcap; extra == 'dev-utils'
Requires-Dist: i2; extra == 'dev-utils'
Requires-Dist: ipython; extra == 'dev-utils'
Requires-Dist: ju; extra == 'dev-utils'
Requires-Dist: jy; extra == 'dev-utils'
Requires-Dist: lkj; extra == 'dev-utils'
Requires-Dist: lxml; extra == 'dev-utils'
Requires-Dist: matplotlib; extra == 'dev-utils'
Requires-Dist: oa; extra == 'dev-utils'
Requires-Dist: pydantic; extra == 'dev-utils'
Requires-Dist: pytest; extra == 'dev-utils'
Requires-Dist: requests; extra == 'dev-utils'
Requires-Dist: tabled; extra == 'dev-utils'
Provides-Extra: test
Requires-Dist: linked; extra == 'test'
